{
	"info": {
		"_postman_id": "48eba7a5-d8b3-4c77-b1cb-1ad022d8b206",
		"name": "Robart",
		"description": "faimware and robort austria",
		"schema": "https://schema.getpostman.com/json/collection/v2.1.0/collection.json"
	},
	"item": [
		{
			"name": "getAllFirmware",
			"request": {
				"auth": {
					"type": "basic",
					"basic": [
						{
							"key": "password",
							"value": "admin",
							"type": "string"
						},
						{
							"key": "username",
							"value": "admin",
							"type": "string"
						}
					]
				},
				"method": "GET",
				"header": [],
				"url": {
					"raw": "http://localhost:8085/firmware/all",
					"protocol": "http",
					"host": [
						"localhost"
					],
					"port": "8085",
					"path": [
						"firmware",
						"all"
					]
				}
			},
			"response": []
		},
		{
			"name": "firmwareUpload",
			"request": {
				"auth": {
					"type": "basic",
					"basic": [
						{
							"key": "password",
							"value": "admin",
							"type": "string"
						},
						{
							"key": "username",
							"value": "admin",
							"type": "string"
						}
					]
				},
				"method": "PUT",
				"header": [],
				"body": {
					"mode": "raw",
					"raw": "{\r\n   \"name\": \"firmware_vishnu\",\r\n    \"data\": \"R29vZCB5b3Uga25vdyBob3cgdG8gZGVjb2RlIGJhc2UgNjAbCd\" \r\n}",
					"options": {
						"raw": {
							"language": "json"
						}
					}
				},
				"url": {
					"raw": "http://localhost:8085/firmware/upload",
					"protocol": "http",
					"host": [
						"localhost"
					],
					"port": "8085",
					"path": [
						"firmware",
						"upload"
					]
				}
			},
			"response": []
		},
		{
			"name": "getAllRobots",
			"request": {
				"auth": {
					"type": "basic",
					"basic": [
						{
							"key": "password",
							"value": "admin",
							"type": "string"
						},
						{
							"key": "username",
							"value": "admin",
							"type": "string"
						}
					]
				},
				"method": "GET",
				"header": [],
				"url": {
					"raw": "http://localhost:8085/robots/all",
					"protocol": "http",
					"host": [
						"localhost"
					],
					"port": "8085",
					"path": [
						"robots",
						"all"
					]
				}
			},
			"response": []
		},
		{
			"name": "firmwareUpdateData",
			"request": {
				"auth": {
					"type": "basic",
					"basic": [
						{
							"key": "password",
							"value": "admin",
							"type": "string"
						},
						{
							"key": "username",
							"value": "admin",
							"type": "string"
						}
					]
				},
				"method": "POST",
				"header": [],
				"body": {
					"mode": "raw",
					"raw": "{\r\n   \"name\": \"firmware_vishnu\",\r\n    \"data\": \"Vishnu12345\"  \r\n}",
					"options": {
						"raw": {
							"language": "json"
						}
					}
				},
				"url": {
					"raw": "http://localhost:8085/firmware/updateData",
					"protocol": "http",
					"host": [
						"localhost"
					],
					"port": "8085",
					"path": [
						"firmware",
						"updateData"
					]
				}
			},
			"response": []
		},
		{
			"name": "firmwareUpdateName",
			"request": {
				"auth": {
					"type": "basic",
					"basic": [
						{
							"key": "password",
							"value": "admin",
							"type": "string"
						},
						{
							"key": "username",
							"value": "admin",
							"type": "string"
						}
					]
				},
				"method": "POST",
				"header": [],
				"body": {
					"mode": "raw",
					"raw": "{\r\n   \"name\": \"vishnu123\",\r\n    \"data\": \"Vishnu12345\"  \r\n}",
					"options": {
						"raw": {
							"language": "json"
						}
					}
				},
				"url": {
					"raw": "http://localhost:8085/firmware/updateName",
					"protocol": "http",
					"host": [
						"localhost"
					],
					"port": "8085",
					"path": [
						"firmware",
						"updateName"
					]
				}
			},
			"response": []
		},
		{
			"name": "firmwareRemove",
			"request": {
				"auth": {
					"type": "basic",
					"basic": [
						{
							"key": "password",
							"value": "admin",
							"type": "string"
						},
						{
							"key": "username",
							"value": "admin",
							"type": "string"
						}
					]
				},
				"method": "DELETE",
				"header": [],
				"url": {
					"raw": "http://localhost:8085/firmware/remove/vishnu123",
					"protocol": "http",
					"host": [
						"localhost"
					],
					"port": "8085",
					"path": [
						"firmware",
						"remove",
						"vishnu123"
					]
				}
			},
			"response": []
		},
		{
			"name": "updateFirmware",
			"request": {
				"auth": {
					"type": "basic",
					"basic": [
						{
							"key": "password",
							"value": "user",
							"type": "string"
						},
						{
							"key": "username",
							"value": "user",
							"type": "string"
						}
					]
				},
				"method": "GET",
				"header": [],
				"url": {
					"raw": "http://localhost:8085/user/update/firmware/robot_1",
					"protocol": "http",
					"host": [
						"localhost"
					],
					"port": "8085",
					"path": [
						"user",
						"update",
						"firmware",
						"robot_1"
					]
				}
			},
			"response": []
		},
		{
			"name": "createMapping",
			"request": {
				"auth": {
					"type": "basic",
					"basic": [
						{
							"key": "password",
							"value": "admin",
							"type": "string"
						},
						{
							"key": "username",
							"value": "admin",
							"type": "string"
						}
					]
				},
				"method": "POST",
				"header": [],
				"body": {
					"mode": "raw",
					"raw": "{\r\n    \"robots\" :[\"robot_1\",\"robot_2\",\"robot_3\"],\r\n    \"firmware\" : \"firmware_upgrade_A_1\"\r\n}",
					"options": {
						"raw": {
							"language": "json"
						}
					}
				},
				"url": {
					"raw": "http://localhost:8085/mapping",
					"protocol": "http",
					"host": [
						"localhost"
					],
					"port": "8085",
					"path": [
						"mapping"
					]
				}
			},
			"response": []
		}
	]
}